{
  "operationConfig" : {
    "name" : "updatecards6142",
    "type" : "MappedToBackend",
    "cachable" : false,
    "smsEnabled" : false,
    "security" : "public",
    "responseEncoding" : "UTF-8",
    "httpMethod" : "GET",
    "decodeResponseBody" : false,
    "referencingEndpoint" : "default",
    "inputs" : [ {
      "id" : "card_id",
      "scope" : "request",
      "dataType" : "number",
      "encode" : true,
      "passNull" : false
    }, {
      "id" : "card_number",
      "scope" : "request",
      "dataType" : "string",
      "encode" : true,
      "passNull" : false
    }, {
      "id" : "account_id",
      "scope" : "request",
      "dataType" : "number",
      "encode" : true,
      "passNull" : false
    } ],
    "iMapping" : "<?xml version=\"1.0\" encoding=\"UTF-8\" standalone=\"yes\"?><mapper xmlns=\"http://www.kony.com/ns/mapper\"><map inputpath=\"request_in\" outputpath=\"request_out\"><exec-function name=\"kony.gen.obj.cards.toLOBFields\"/><exec-function name=\"kony.gen.obj.cards__metadata.toLOBFields\"/><map inputpath=\"transactions\" outputpath=\"transactions\"><exec-function name=\"kony.gen.obj.transactions.toLOBFields\"/><exec-function name=\"kony.gen.obj.transactions__metadata.toLOBFields\"/></map></map></mapper>",
    "oMapping" : "<?xml version=\"1.0\" encoding=\"UTF-8\" standalone=\"yes\"?><mapper xmlns=\"http://www.kony.com/ns/mapper\"><map inputpath=\"response_in\" outputpath=\"response_out\"><map inputpath=\"cards\" outputpath=\"cards\"><exec-function name=\"kony.gen.obj.cards.fromLOBFields\"/><map inputpath=\"transactions\" outputpath=\"transactions\"><exec-function name=\"kony.gen.obj.transactions.fromLOBFields\"/></map></map></map></mapper>",
    "applyCommonMapping" : true,
    "applyRequestCommonMapping" : true,
    "applyResponseCommonMapping" : true,
    "entityMetadata" : "{\"entityAttributeTypeList\":[{\"name\":\"card_id\",\"jdbcType\":4,\"columnTypeName\":\"INT\",\"columnDecimalDigits\":0,\"autoGenerated\":true,\"creatable\":false,\"updatable\":false,\"primary\":true,\"softDelete\":false,\"lastModified\":false},{\"name\":\"card_number\",\"jdbcType\":12,\"columnTypeName\":\"VARCHAR\",\"columnDecimalDigits\":0,\"autoGenerated\":false,\"creatable\":true,\"updatable\":true,\"primary\":false,\"softDelete\":false,\"lastModified\":false},{\"name\":\"account_id\",\"jdbcType\":4,\"columnTypeName\":\"INT\",\"columnDecimalDigits\":0,\"autoGenerated\":false,\"creatable\":true,\"updatable\":true,\"primary\":false,\"softDelete\":false,\"lastModified\":false}],\"relationshipTypeList\":[{\"targetEntityType\":{\"name\":\"transactions\",\"schemaName\":\"anonymousdb\"},\"relationshipAttributeTypeList\":[{\"sourceEntityAttributeType\":{\"name\":\"card_id\",\"jdbcType\":0,\"columnDecimalDigits\":0,\"autoGenerated\":false,\"creatable\":false,\"updatable\":false,\"primary\":false,\"softDelete\":false,\"lastModified\":false},\"targetEntityAttributeType\":{\"name\":\"card_id\",\"jdbcType\":0,\"columnDecimalDigits\":0,\"autoGenerated\":false,\"creatable\":false,\"updatable\":false,\"primary\":false,\"softDelete\":false,\"lastModified\":false}}],\"cascadeDelete\":false,\"relationshipType\":\"ONE_TO_MANY\"}],\"name\":\"cards\",\"schemaName\":\"anonymousdb\",\"entityType\":\"com.kony.rdbms.metadata.model.AnnotatedTable\"}",
    "opcode" : "update",
    "backendMeta" : {
      "qualifiedObjectName" : "anonymousdb.cards",
      "backendObjectName" : "cards"
    },
    "relationshipHierarchyMapping" : {
      "children" : [ {
        "actionsAllSelected" : true,
        "children" : [ ],
        "name" : "transactions",
        "actions" : {
          "create" : true,
          "update" : true,
          "delete" : true
        },
        "actionsPartiallySelected" : false,
        "selected" : true
      } ],
      "name" : "cards",
      "actions" : {
        "create" : true,
        "update" : true,
        "delete" : true
      },
      "selected" : true
    },
    "requestXmlMappingOverride" : false,
    "responseXmlMappingOverride" : false
  }
}